cssfinder_backend_numpy/__init__.py
cssfinder_backend_numpy/_cython/__init__.py
cssfinder_backend_numpy/_cython/_complex128.py
cssfinder_backend_numpy/_cython/_complex64.py
cssfinder_backend_numpy/base.py
cssfinder_backend_numpy/complex128.py
cssfinder_backend_numpy/complex64.py
cssfinder_backend_numpy/cython/__init__.py
cssfinder_backend_numpy/cython/_complex128.cpython-39-x86_64-linux-gnu.so
cssfinder_backend_numpy/cython/_complex64.cpython-39-x86_64-linux-gnu.so
cssfinder_backend_numpy/impl.py
cssfinder_backend_numpy/numpy/__init__.py
cssfinder_backend_numpy/numpy/_complex128.py
cssfinder_backend_numpy/numpy/_complex64.py
cssfinder_backend_numpy/numpy_debug/__init__.py
cssfinder_backend_numpy/numpy_debug/_complex128.py
cssfinder_backend_numpy/numpy_debug/_complex64.py
cssfinder_backend_numpy/numpy_jit/__init__.py
cssfinder_backend_numpy/numpy_jit/_complex128.py
cssfinder_backend_numpy/numpy_jit/_complex64.py
cssfinder_backend_numpy-0.5.0.dist-info/METADATA
cssfinder_backend_numpy-0.5.0.dist-info/WHEEL
cssfinder_backend_numpy-0.5.0.dist-info/entry_points.txt
cssfinder_backend_numpy-0.5.0.dist-info/RECORD
