Metadata-Version: 2.1
Name: cssfinder-backend-numpy
Version: 0.5.0
Summary: Implementation of CSSFinder backend using NumPy library.
Home-page: https://github.com/argmaster/cssfinder_backend_numpy
Author: Krzysztof Wiśniewski
Author-email: argmaster.world@gmail.com
Requires-Python: >=3.8,<4.0
Classifier: Programming Language :: Python :: 3
Classifier: Programming Language :: Python :: 3.8
Classifier: Programming Language :: Python :: 3.9
Classifier: Programming Language :: Python :: 3.10
Classifier: Programming Language :: Python :: 3.11
Requires-Dist: cssfinder (>=0.4.0)
Requires-Dist: numba (>=0.56.4,<0.57.0)
Requires-Dist: numpy (>=1.23.0,<2.0.0)
Requires-Dist: typing-extensions (>=4.5.0,<5.0.0)
Project-URL: Repository, https://github.com/argmaster/cssfinder_backend_numpy
